{
  "version": 1,
  "parameters": "--include-transitive",
  "projects": [
    {
      "path": "/home/runner/work/pkgchk-cli/pkgchk-cli/src/pkgchk-cli.fsproj",
      "frameworks": [
        {
          "framework": "net7.0",
          "topLevelPackages": [
            {
              "id": "FSharp.Core",
              "requestedVersion": "8.0.100",
              "resolvedVersion": "8.0.100"
            },
            {
              "id": "FSharp.Data",
              "requestedVersion": "6.3.0",
              "resolvedVersion": "6.3.0"
            },
            {
              "id": "Spectre.Console.Cli",
              "requestedVersion": "0.48.0",
              "resolvedVersion": "0.48.0"
            }
          ],
          "transitivePackages": [
            {
              "id": "FSharp.Data.Csv.Core",
              "resolvedVersion": "6.3.0"
            },
            {
              "id": "FSharp.Data.Html.Core",
              "resolvedVersion": "6.3.0"
            },
            {
              "id": "FSharp.Data.Http",
              "resolvedVersion": "6.3.0"
            },
            {
              "id": "FSharp.Data.Json.Core",
              "resolvedVersion": "6.3.0"
            },
            {
              "id": "FSharp.Data.Runtime.Utilities",
              "resolvedVersion": "6.3.0"
            },
            {
              "id": "FSharp.Data.WorldBank.Core",
              "resolvedVersion": "6.3.0"
            },
            {
              "id": "FSharp.Data.Xml.Core",
              "resolvedVersion": "6.3.0"
            },
            {
              "id": "Spectre.Console",
              "resolvedVersion": "0.48.0"
            },
            {
              "id": "System.Memory",
              "resolvedVersion": "4.5.5"
            }
          ]
        }
      ]
    },
    {
      "path": "/home/runner/work/pkgchk-cli/pkgchk-cli/tests/pkgchk-cli.tests/pkgchk-cli.tests.fsproj",
      "frameworks": [
        {
          "framework": "net7.0",
          "topLevelPackages": [
            {
              "id": "coverlet.collector",
              "requestedVersion": "6.0.0",
              "resolvedVersion": "6.0.0"
            },
            {
              "id": "coverlet.msbuild",
              "requestedVersion": "6.0.0",
              "resolvedVersion": "6.0.0"
            },
            {
              "id": "FsCheck.Xunit",
              "requestedVersion": "2.16.6",
              "resolvedVersion": "2.16.6"
            },
            {
              "id": "FSharp.Core",
              "requestedVersion": "8.0.100",
              "resolvedVersion": "8.0.100"
            },
            {
              "id": "FsUnit.xUnit",
              "requestedVersion": "5.6.1",
              "resolvedVersion": "5.6.1"
            },
            {
              "id": "Microsoft.NET.Test.Sdk",
              "requestedVersion": "17.8.0",
              "resolvedVersion": "17.8.0"
            },
            {
              "id": "NSubstitute",
              "requestedVersion": "5.1.0",
              "resolvedVersion": "5.1.0"
            },
            {
              "id": "System.Net.Http",
              "requestedVersion": "4.3.4",
              "resolvedVersion": "4.3.4"
            },
            {
              "id": "System.Text.RegularExpressions",
              "requestedVersion": "4.3.1",
              "resolvedVersion": "4.3.1"
            },
            {
              "id": "xunit",
              "requestedVersion": "2.6.3",
              "resolvedVersion": "2.6.3"
            },
            {
              "id": "xunit.runner.visualstudio",
              "requestedVersion": "2.5.5",
              "resolvedVersion": "2.5.5"
            }
          ],
          "transitivePackages": [
            {
              "id": "Castle.Core",
              "resolvedVersion": "5.1.1"
            },
            {
              "id": "FsCheck",
              "resolvedVersion": "2.16.6"
            },
            {
              "id": "FSharp.Data",
              "resolvedVersion": "6.3.0"
            },
            {
              "id": "FSharp.Data.Csv.Core",
              "resolvedVersion": "6.3.0"
            },
            {
              "id": "FSharp.Data.Html.Core",
              "resolvedVersion": "6.3.0"
            },
            {
              "id": "FSharp.Data.Http",
              "resolvedVersion": "6.3.0"
            },
            {
              "id": "FSharp.Data.Json.Core",
              "resolvedVersion": "6.3.0"
            },
            {
              "id": "FSharp.Data.Runtime.Utilities",
              "resolvedVersion": "6.3.0"
            },
            {
              "id": "FSharp.Data.WorldBank.Core",
              "resolvedVersion": "6.3.0"
            },
            {
              "id": "FSharp.Data.Xml.Core",
              "resolvedVersion": "6.3.0"
            },
            {
              "id": "Microsoft.CodeCoverage",
              "resolvedVersion": "17.8.0"
            },
            {
              "id": "Microsoft.NETCore.Platforms",
              "resolvedVersion": "1.1.1"
            },
            {
              "id": "Microsoft.NETCore.Targets",
              "resolvedVersion": "1.1.3"
            },
            {
              "id": "Microsoft.TestPlatform.ObjectModel",
              "resolvedVersion": "17.8.0"
            },
            {
              "id": "Microsoft.TestPlatform.TestHost",
              "resolvedVersion": "17.8.0"
            },
            {
              "id": "Microsoft.Win32.Primitives",
              "resolvedVersion": "4.3.0"
            },
            {
              "id": "NETStandard.Library",
              "resolvedVersion": "1.6.1"
            },
            {
              "id": "Newtonsoft.Json",
              "resolvedVersion": "13.0.1"
            },
            {
              "id": "NHamcrest",
              "resolvedVersion": "3.4.0"
            },
            {
              "id": "NuGet.Frameworks",
              "resolvedVersion": "6.5.0"
            },
            {
              "id": "runtime.debian.8-x64.runtime.native.System.Security.Cryptography.OpenSsl",
              "resolvedVersion": "4.3.2"
            },
            {
              "id": "runtime.fedora.23-x64.runtime.native.System.Security.Cryptography.OpenSsl",
              "resolvedVersion": "4.3.2"
            },
            {
              "id": "runtime.fedora.24-x64.runtime.native.System.Security.Cryptography.OpenSsl",
              "resolvedVersion": "4.3.2"
            },
            {
              "id": "runtime.native.System",
              "resolvedVersion": "4.3.0"
            },
            {
              "id": "runtime.native.System.IO.Compression",
              "resolvedVersion": "4.3.0"
            },
            {
              "id": "runtime.native.System.Net.Http",
              "resolvedVersion": "4.3.0"
            },
            {
              "id": "runtime.native.System.Security.Cryptography.Apple",
              "resolvedVersion": "4.3.0"
            },
            {
              "id": "runtime.native.System.Security.Cryptography.OpenSsl",
              "resolvedVersion": "4.3.2"
            },
            {
              "id": "runtime.opensuse.13.2-x64.runtime.native.System.Security.Cryptography.OpenSsl",
              "resolvedVersion": "4.3.2"
            },
            {
              "id": "runtime.opensuse.42.1-x64.runtime.native.System.Security.Cryptography.OpenSsl",
              "resolvedVersion": "4.3.2"
            },
            {
              "id": "runtime.osx.10.10-x64.runtime.native.System.Security.Cryptography.Apple",
              "resolvedVersion": "4.3.0"
            },
            {
              "id": "runtime.osx.10.10-x64.runtime.native.System.Security.Cryptography.OpenSsl",
              "resolvedVersion": "4.3.2"
            },
            {
              "id": "runtime.rhel.7-x64.runtime.native.System.Security.Cryptography.OpenSsl",
              "resolvedVersion": "4.3.2"
            },
            {
              "id": "runtime.ubuntu.14.04-x64.runtime.native.System.Security.Cryptography.OpenSsl",
              "resolvedVersion": "4.3.2"
            },
            {
              "id": "runtime.ubuntu.16.04-x64.runtime.native.System.Security.Cryptography.OpenSsl",
              "resolvedVersion": "4.3.2"
            },
            {
              "id": "runtime.ubuntu.16.10-x64.runtime.native.System.Security.Cryptography.OpenSsl",
              "resolvedVersion": "4.3.2"
            },
            {
              "id": "Spectre.Console",
              "resolvedVersion": "0.48.0"
            },
            {
              "id": "Spectre.Console.Cli",
              "resolvedVersion": "0.48.0"
            },
            {
              "id": "System.AppContext",
              "resolvedVersion": "4.3.0"
            },
            {
              "id": "System.Buffers",
              "resolvedVersion": "4.3.0"
            },
            {
              "id": "System.Collections",
              "resolvedVersion": "4.3.0"
            },
            {
              "id": "System.Collections.Concurrent",
              "resolvedVersion": "4.3.0"
            },
            {
              "id": "System.Console",
              "resolvedVersion": "4.3.0"
            },
            {
              "id": "System.Diagnostics.Debug",
              "resolvedVersion": "4.3.0"
            },
            {
              "id": "System.Diagnostics.DiagnosticSource",
              "resolvedVersion": "4.3.0"
            },
            {
              "id": "System.Diagnostics.EventLog",
              "resolvedVersion": "6.0.0"
            },
            {
              "id": "System.Diagnostics.Tools",
              "resolvedVersion": "4.3.0"
            },
            {
              "id": "System.Diagnostics.Tracing",
              "resolvedVersion": "4.3.0"
            },
            {
              "id": "System.Globalization",
              "resolvedVersion": "4.3.0"
            },
            {
              "id": "System.Globalization.Calendars",
              "resolvedVersion": "4.3.0"
            },
            {
              "id": "System.Globalization.Extensions",
              "resolvedVersion": "4.3.0"
            },
            {
              "id": "System.IO",
              "resolvedVersion": "4.3.0"
            },
            {
              "id": "System.IO.Compression",
              "resolvedVersion": "4.3.0"
            },
            {
              "id": "System.IO.Compression.ZipFile",
              "resolvedVersion": "4.3.0"
            },
            {
              "id": "System.IO.FileSystem",
              "resolvedVersion": "4.3.0"
            },
            {
              "id": "System.IO.FileSystem.Primitives",
              "resolvedVersion": "4.3.0"
            },
            {
              "id": "System.Linq",
              "resolvedVersion": "4.3.0"
            },
            {
              "id": "System.Linq.Expressions",
              "resolvedVersion": "4.3.0"
            },
            {
              "id": "System.Memory",
              "resolvedVersion": "4.5.5"
            },
            {
              "id": "System.Net.Primitives",
              "resolvedVersion": "4.3.0"
            },
            {
              "id": "System.Net.Sockets",
              "resolvedVersion": "4.3.0"
            },
            {
              "id": "System.ObjectModel",
              "resolvedVersion": "4.3.0"
            },
            {
              "id": "System.Reflection",
              "resolvedVersion": "4.3.0"
            },
            {
              "id": "System.Reflection.Emit",
              "resolvedVersion": "4.3.0"
            },
            {
              "id": "System.Reflection.Emit.ILGeneration",
              "resolvedVersion": "4.3.0"
            },
            {
              "id": "System.Reflection.Emit.Lightweight",
              "resolvedVersion": "4.3.0"
            },
            {
              "id": "System.Reflection.Extensions",
              "resolvedVersion": "4.3.0"
            },
            {
              "id": "System.Reflection.Metadata",
              "resolvedVersion": "1.6.0"
            },
            {
              "id": "System.Reflection.Primitives",
              "resolvedVersion": "4.3.0"
            },
            {
              "id": "System.Reflection.TypeExtensions",
              "resolvedVersion": "4.3.0"
            },
            {
              "id": "System.Resources.ResourceManager",
              "resolvedVersion": "4.3.0"
            },
            {
              "id": "System.Runtime",
              "resolvedVersion": "4.3.1"
            },
            {
              "id": "System.Runtime.Extensions",
              "resolvedVersion": "4.3.0"
            },
            {
              "id": "System.Runtime.Handles",
              "resolvedVersion": "4.3.0"
            },
            {
              "id": "System.Runtime.InteropServices",
              "resolvedVersion": "4.3.0"
            },
            {
              "id": "System.Runtime.InteropServices.RuntimeInformation",
              "resolvedVersion": "4.3.0"
            },
            {
              "id": "System.Runtime.Numerics",
              "resolvedVersion": "4.3.0"
            },
            {
              "id": "System.Security.Cryptography.Algorithms",
              "resolvedVersion": "4.3.0"
            },
            {
              "id": "System.Security.Cryptography.Cng",
              "resolvedVersion": "4.3.0"
            },
            {
              "id": "System.Security.Cryptography.Csp",
              "resolvedVersion": "4.3.0"
            },
            {
              "id": "System.Security.Cryptography.Encoding",
              "resolvedVersion": "4.3.0"
            },
            {
              "id": "System.Security.Cryptography.OpenSsl",
              "resolvedVersion": "4.3.0"
            },
            {
              "id": "System.Security.Cryptography.Primitives",
              "resolvedVersion": "4.3.0"
            },
            {
              "id": "System.Security.Cryptography.X509Certificates",
              "resolvedVersion": "4.3.0"
            },
            {
              "id": "System.Text.Encoding",
              "resolvedVersion": "4.3.0"
            },
            {
              "id": "System.Text.Encoding.Extensions",
              "resolvedVersion": "4.3.0"
            },
            {
              "id": "System.Threading",
              "resolvedVersion": "4.3.0"
            },
            {
              "id": "System.Threading.Tasks",
              "resolvedVersion": "4.3.0"
            },
            {
              "id": "System.Threading.Tasks.Extensions",
              "resolvedVersion": "4.3.0"
            },
            {
              "id": "System.Threading.Timer",
              "resolvedVersion": "4.3.0"
            },
            {
              "id": "System.Xml.ReaderWriter",
              "resolvedVersion": "4.3.0"
            },
            {
              "id": "System.Xml.XDocument",
              "resolvedVersion": "4.3.0"
            },
            {
              "id": "xunit.abstractions",
              "resolvedVersion": "2.0.3"
            },
            {
              "id": "xunit.analyzers",
              "resolvedVersion": "1.7.0"
            },
            {
              "id": "xunit.assert",
              "resolvedVersion": "2.6.3"
            },
            {
              "id": "xunit.core",
              "resolvedVersion": "2.6.3"
            },
            {
              "id": "xunit.extensibility.core",
              "resolvedVersion": "2.6.3"
            },
            {
              "id": "xunit.extensibility.execution",
              "resolvedVersion": "2.6.3"
            }
          ]
        }
      ]
    },
    {
      "path": "/home/runner/work/pkgchk-cli/pkgchk-cli/tests/pkgchk-cli.tests.integration/pkgchk-cli.tests.integration.fsproj",
      "frameworks": [
        {
          "framework": "net7.0",
          "topLevelPackages": [
            {
              "id": "coverlet.collector",
              "requestedVersion": "6.0.0",
              "resolvedVersion": "6.0.0"
            },
            {
              "id": "coverlet.msbuild",
              "requestedVersion": "6.0.0",
              "resolvedVersion": "6.0.0"
            },
            {
              "id": "FsCheck.Xunit",
              "requestedVersion": "2.16.6",
              "resolvedVersion": "2.16.6"
            },
            {
              "id": "FSharp.Core",
              "requestedVersion": "8.0.100",
              "resolvedVersion": "8.0.100"
            },
            {
              "id": "FsUnit.xUnit",
              "requestedVersion": "5.6.1",
              "resolvedVersion": "5.6.1"
            },
            {
              "id": "Microsoft.NET.Test.Sdk",
              "requestedVersion": "17.8.0",
              "resolvedVersion": "17.8.0"
            },
            {
              "id": "NSubstitute",
              "requestedVersion": "5.1.0",
              "resolvedVersion": "5.1.0"
            },
            {
              "id": "System.Net.Http",
              "requestedVersion": "4.3.4",
              "resolvedVersion": "4.3.4"
            },
            {
              "id": "System.Text.RegularExpressions",
              "requestedVersion": "4.3.1",
              "resolvedVersion": "4.3.1"
            },
            {
              "id": "xunit",
              "requestedVersion": "2.6.3",
              "resolvedVersion": "2.6.3"
            },
            {
              "id": "xunit.runner.visualstudio",
              "requestedVersion": "2.5.5",
              "resolvedVersion": "2.5.5"
            }
          ],
          "transitivePackages": [
            {
              "id": "Castle.Core",
              "resolvedVersion": "5.1.1"
            },
            {
              "id": "FsCheck",
              "resolvedVersion": "2.16.6"
            },
            {
              "id": "FSharp.Data",
              "resolvedVersion": "6.3.0"
            },
            {
              "id": "FSharp.Data.Csv.Core",
              "resolvedVersion": "6.3.0"
            },
            {
              "id": "FSharp.Data.Html.Core",
              "resolvedVersion": "6.3.0"
            },
            {
              "id": "FSharp.Data.Http",
              "resolvedVersion": "6.3.0"
            },
            {
              "id": "FSharp.Data.Json.Core",
              "resolvedVersion": "6.3.0"
            },
            {
              "id": "FSharp.Data.Runtime.Utilities",
              "resolvedVersion": "6.3.0"
            },
            {
              "id": "FSharp.Data.WorldBank.Core",
              "resolvedVersion": "6.3.0"
            },
            {
              "id": "FSharp.Data.Xml.Core",
              "resolvedVersion": "6.3.0"
            },
            {
              "id": "Microsoft.CodeCoverage",
              "resolvedVersion": "17.8.0"
            },
            {
              "id": "Microsoft.NETCore.Platforms",
              "resolvedVersion": "1.1.1"
            },
            {
              "id": "Microsoft.NETCore.Targets",
              "resolvedVersion": "1.1.3"
            },
            {
              "id": "Microsoft.TestPlatform.ObjectModel",
              "resolvedVersion": "17.8.0"
            },
            {
              "id": "Microsoft.TestPlatform.TestHost",
              "resolvedVersion": "17.8.0"
            },
            {
              "id": "Microsoft.Win32.Primitives",
              "resolvedVersion": "4.3.0"
            },
            {
              "id": "NETStandard.Library",
              "resolvedVersion": "1.6.1"
            },
            {
              "id": "Newtonsoft.Json",
              "resolvedVersion": "13.0.1"
            },
            {
              "id": "NHamcrest",
              "resolvedVersion": "3.4.0"
            },
            {
              "id": "NuGet.Frameworks",
              "resolvedVersion": "6.5.0"
            },
            {
              "id": "runtime.debian.8-x64.runtime.native.System.Security.Cryptography.OpenSsl",
              "resolvedVersion": "4.3.2"
            },
            {
              "id": "runtime.fedora.23-x64.runtime.native.System.Security.Cryptography.OpenSsl",
              "resolvedVersion": "4.3.2"
            },
            {
              "id": "runtime.fedora.24-x64.runtime.native.System.Security.Cryptography.OpenSsl",
              "resolvedVersion": "4.3.2"
            },
            {
              "id": "runtime.native.System",
              "resolvedVersion": "4.3.0"
            },
            {
              "id": "runtime.native.System.IO.Compression",
              "resolvedVersion": "4.3.0"
            },
            {
              "id": "runtime.native.System.Net.Http",
              "resolvedVersion": "4.3.0"
            },
            {
              "id": "runtime.native.System.Security.Cryptography.Apple",
              "resolvedVersion": "4.3.0"
            },
            {
              "id": "runtime.native.System.Security.Cryptography.OpenSsl",
              "resolvedVersion": "4.3.2"
            },
            {
              "id": "runtime.opensuse.13.2-x64.runtime.native.System.Security.Cryptography.OpenSsl",
              "resolvedVersion": "4.3.2"
            },
            {
              "id": "runtime.opensuse.42.1-x64.runtime.native.System.Security.Cryptography.OpenSsl",
              "resolvedVersion": "4.3.2"
            },
            {
              "id": "runtime.osx.10.10-x64.runtime.native.System.Security.Cryptography.Apple",
              "resolvedVersion": "4.3.0"
            },
            {
              "id": "runtime.osx.10.10-x64.runtime.native.System.Security.Cryptography.OpenSsl",
              "resolvedVersion": "4.3.2"
            },
            {
              "id": "runtime.rhel.7-x64.runtime.native.System.Security.Cryptography.OpenSsl",
              "resolvedVersion": "4.3.2"
            },
            {
              "id": "runtime.ubuntu.14.04-x64.runtime.native.System.Security.Cryptography.OpenSsl",
              "resolvedVersion": "4.3.2"
            },
            {
              "id": "runtime.ubuntu.16.04-x64.runtime.native.System.Security.Cryptography.OpenSsl",
              "resolvedVersion": "4.3.2"
            },
            {
              "id": "runtime.ubuntu.16.10-x64.runtime.native.System.Security.Cryptography.OpenSsl",
              "resolvedVersion": "4.3.2"
            },
            {
              "id": "Spectre.Console",
              "resolvedVersion": "0.48.0"
            },
            {
              "id": "Spectre.Console.Cli",
              "resolvedVersion": "0.48.0"
            },
            {
              "id": "System.AppContext",
              "resolvedVersion": "4.3.0"
            },
            {
              "id": "System.Buffers",
              "resolvedVersion": "4.3.0"
            },
            {
              "id": "System.Collections",
              "resolvedVersion": "4.3.0"
            },
            {
              "id": "System.Collections.Concurrent",
              "resolvedVersion": "4.3.0"
            },
            {
              "id": "System.Console",
              "resolvedVersion": "4.3.0"
            },
            {
              "id": "System.Diagnostics.Debug",
              "resolvedVersion": "4.3.0"
            },
            {
              "id": "System.Diagnostics.DiagnosticSource",
              "resolvedVersion": "4.3.0"
            },
            {
              "id": "System.Diagnostics.EventLog",
              "resolvedVersion": "6.0.0"
            },
            {
              "id": "System.Diagnostics.Tools",
              "resolvedVersion": "4.3.0"
            },
            {
              "id": "System.Diagnostics.Tracing",
              "resolvedVersion": "4.3.0"
            },
            {
              "id": "System.Globalization",
              "resolvedVersion": "4.3.0"
            },
            {
              "id": "System.Globalization.Calendars",
              "resolvedVersion": "4.3.0"
            },
            {
              "id": "System.Globalization.Extensions",
              "resolvedVersion": "4.3.0"
            },
            {
              "id": "System.IO",
              "resolvedVersion": "4.3.0"
            },
            {
              "id": "System.IO.Compression",
              "resolvedVersion": "4.3.0"
            },
            {
              "id": "System.IO.Compression.ZipFile",
              "resolvedVersion": "4.3.0"
            },
            {
              "id": "System.IO.FileSystem",
              "resolvedVersion": "4.3.0"
            },
            {
              "id": "System.IO.FileSystem.Primitives",
              "resolvedVersion": "4.3.0"
            },
            {
              "id": "System.Linq",
              "resolvedVersion": "4.3.0"
            },
            {
              "id": "System.Linq.Expressions",
              "resolvedVersion": "4.3.0"
            },
            {
              "id": "System.Memory",
              "resolvedVersion": "4.5.5"
            },
            {
              "id": "System.Net.Primitives",
              "resolvedVersion": "4.3.0"
            },
            {
              "id": "System.Net.Sockets",
              "resolvedVersion": "4.3.0"
            },
            {
              "id": "System.ObjectModel",
              "resolvedVersion": "4.3.0"
            },
            {
              "id": "System.Reflection",
              "resolvedVersion": "4.3.0"
            },
            {
              "id": "System.Reflection.Emit",
              "resolvedVersion": "4.3.0"
            },
            {
              "id": "System.Reflection.Emit.ILGeneration",
              "resolvedVersion": "4.3.0"
            },
            {
              "id": "System.Reflection.Emit.Lightweight",
              "resolvedVersion": "4.3.0"
            },
            {
              "id": "System.Reflection.Extensions",
              "resolvedVersion": "4.3.0"
            },
            {
              "id": "System.Reflection.Metadata",
              "resolvedVersion": "1.6.0"
            },
            {
              "id": "System.Reflection.Primitives",
              "resolvedVersion": "4.3.0"
            },
            {
              "id": "System.Reflection.TypeExtensions",
              "resolvedVersion": "4.3.0"
            },
            {
              "id": "System.Resources.ResourceManager",
              "resolvedVersion": "4.3.0"
            },
            {
              "id": "System.Runtime",
              "resolvedVersion": "4.3.1"
            },
            {
              "id": "System.Runtime.Extensions",
              "resolvedVersion": "4.3.0"
            },
            {
              "id": "System.Runtime.Handles",
              "resolvedVersion": "4.3.0"
            },
            {
              "id": "System.Runtime.InteropServices",
              "resolvedVersion": "4.3.0"
            },
            {
              "id": "System.Runtime.InteropServices.RuntimeInformation",
              "resolvedVersion": "4.3.0"
            },
            {
              "id": "System.Runtime.Numerics",
              "resolvedVersion": "4.3.0"
            },
            {
              "id": "System.Security.Cryptography.Algorithms",
              "resolvedVersion": "4.3.0"
            },
            {
              "id": "System.Security.Cryptography.Cng",
              "resolvedVersion": "4.3.0"
            },
            {
              "id": "System.Security.Cryptography.Csp",
              "resolvedVersion": "4.3.0"
            },
            {
              "id": "System.Security.Cryptography.Encoding",
              "resolvedVersion": "4.3.0"
            },
            {
              "id": "System.Security.Cryptography.OpenSsl",
              "resolvedVersion": "4.3.0"
            },
            {
              "id": "System.Security.Cryptography.Primitives",
              "resolvedVersion": "4.3.0"
            },
            {
              "id": "System.Security.Cryptography.X509Certificates",
              "resolvedVersion": "4.3.0"
            },
            {
              "id": "System.Text.Encoding",
              "resolvedVersion": "4.3.0"
            },
            {
              "id": "System.Text.Encoding.Extensions",
              "resolvedVersion": "4.3.0"
            },
            {
              "id": "System.Threading",
              "resolvedVersion": "4.3.0"
            },
            {
              "id": "System.Threading.Tasks",
              "resolvedVersion": "4.3.0"
            },
            {
              "id": "System.Threading.Tasks.Extensions",
              "resolvedVersion": "4.3.0"
            },
            {
              "id": "System.Threading.Timer",
              "resolvedVersion": "4.3.0"
            },
            {
              "id": "System.Xml.ReaderWriter",
              "resolvedVersion": "4.3.0"
            },
            {
              "id": "System.Xml.XDocument",
              "resolvedVersion": "4.3.0"
            },
            {
              "id": "xunit.abstractions",
              "resolvedVersion": "2.0.3"
            },
            {
              "id": "xunit.analyzers",
              "resolvedVersion": "1.7.0"
            },
            {
              "id": "xunit.assert",
              "resolvedVersion": "2.6.3"
            },
            {
              "id": "xunit.core",
              "resolvedVersion": "2.6.3"
            },
            {
              "id": "xunit.extensibility.core",
              "resolvedVersion": "2.6.3"
            },
            {
              "id": "xunit.extensibility.execution",
              "resolvedVersion": "2.6.3"
            }
          ]
        }
      ]
    }
  ]
}
